AppDT/__init__.py
AppDT/whlcode.py
appdt-3.0.0.dist-info/licenses/LICENSE
appdt-3.0.0.dist-info/METADATA
appdt-3.0.0.dist-info/WHEEL
appdt-3.0.0.dist-info/entry_points.txt
appdt-3.0.0.dist-info/top_level.txt
appdt-3.0.0.dist-info/RECORD
